[
  {
    "title": "Google Fonts",
    "url": "https://fonts.google.com/",
    "description": "",
    "category": "design/fonts",
    "tags": ["免费字体", "网页字体", "开源字体"],
    "featured": false,
    "icon": "https://fonts.google.com/favicon.ico",
    "id": "mbg9i3dujvs45xu20x8",
    "createdAt": "2025-06-03T08:33:55.362Z",
    "updatedAt": "2025-06-03T08:33:55.362Z"
  },
  {
    "title": "阿里巴巴普惠体",
    "url": "https://www.alibabafonts.com/",
    "description": "永久免费正版商用字体",
    "category": "design/fonts",
    "tags": ["免费字体", "商用字体", "中文字体"],
    "featured": false,
    "icon": "https://img.alicdn.com/imgextra/i1/O1CN01HY7EQy26toOqSOX1T_!!6000000007720-2-tps-64-64.png",
    "id": "mbg9izvrqefeidav70s",
    "createdAt": "2025-06-03T08:34:37.479Z",
    "updatedAt": "2025-06-03T08:34:37.479Z"
  },
  {
    "title": "Font Squirrel",
    "url": "https://www.fontsquirrel.com/",
    "description": "Handpicked free fonts for graphic designers with commercial-use licenses.",
    "category": "design/fonts",
    "tags": ["免费字体", "商用授权", "精选字体"],
    "featured": false,
    "icon": "https://www.fontsquirrel.com/favicon-32x32.png?v=2",
    "id": "mbg9k0wnq1unz3f60c",
    "createdAt": "2025-06-03T08:35:25.463Z",
    "updatedAt": "2025-06-03T08:35:25.463Z"
  },
  {
    "title": "字由",
    "url": "https://www.hellofont.cn/",
    "description": "字由是免费的字体管理工具，为您提供900+字体免费商用，支持在PS、AI、ID、XD、Figma、Sketch、CDR等设计软件中一键应用字体，提供AI识字、字体特效等实用功能，为您的设计提质加速，超百万设计师正在使用字由",
    "category": "design/fonts",
    "tags": ["字体管理", "免费商用", "设计工具"],
    "featured": false,
    "icon": "https://www.hellofont.cn/favicon.ico",
    "id": "mbg9nbb0yxbhndub9ye",
    "createdAt": "2025-06-03T08:37:58.908Z",
    "updatedAt": "2025-06-03T08:37:58.908Z"
  },
  {
    "title": "求字体网",
    "url": "https://www.qiuziti.com/",
    "description": "求字体网提供字体识别,字体预览,免费字体下载,字体在线设计,书法字体,艺术字体,字体大全,手写字体,PS字体,字体转换器等找字体必备工具服务",
    "category": "design/fonts",
    "tags": ["字体查询", "字体识别", "字体下载"],
    "featured": false,
    "icon": "https://www.qiuziti.com/image/icon.ico",
    "id": "mbg9oewz5m7ism1xtk",
    "createdAt": "2025-06-03T08:38:50.243Z",
    "updatedAt": "2025-06-03T08:38:50.243Z"
  }
]
