{
  "id": "productivity",
  "title": "效率工具",
  "description": "提高工作效率的应用和服务",
  "links": [
    {
      "id": "notion",
      "title": "Notion",
      "description": "集笔记、知识库、任务管理于一体的协作平台，提高团队协作效率",
      "url": "https://www.notion.so",
      "tags": ["全能工具", "笔记", "协作"],
      "featured": true
    },
    {
      "id": "trello",
      "title": "Trello",
      "description": "可视化项目管理工具，基于看板方法组织任务和工作流程",
      "url": "https://trello.com",
      "tags": ["项目管理", "看板", "协作"],
      "featured": true
    },
    {
      "id": "todoist",
      "title": "Todoist",
      "description": "简洁高效的任务管理应用，帮助用户组织日常工作和生活",
      "url": "https://todoist.com",
      "tags": ["任务管理", "待办事项", "生产力"]
    },
    {
      "id": "obsidian",
      "title": "Obsidian",
      "description": "基于本地Markdown文件的知识库工具，支持双向链接和图谱可视化",
      "url": "https://obsidian.md",
      "tags": ["知识管理", "笔记", "Markdown"]
    },
    {
      "id": "grammarly",
      "title": "Grammarly",
      "description": "AI驱动的写作助手，提供拼写、语法检查和写作建议",
      "url": "https://www.grammarly.com",
      "tags": ["写作工具", "AI", "语法检查"]
    },
    {
      "id": "calendly",
      "title": "Calendly",
      "description": "智能日程安排工具，简化会议预约流程，避免来回邮件沟通",
      "url": "https://calendly.com",
      "tags": ["日程管理", "会议", "预约"]
    }
  ]
}
